<?xml version="1.0" encoding="UTF-8"?>
<objects serializationModel="Studio.02.01.00">
	<object class="Event" id="{fadbde7c-96ea-48fb-aefd-af5beb834d2e}">
		<property name="name">
			<value>Computer_beeps</value>
		</property>
		<property name="outputFormat">
			<value>1</value>
		</property>
		<relationship name="folder">
			<destination>{e38beb2c-8d64-43e0-bd5e-3020afbddad3}</destination>
		</relationship>
		<relationship name="mixer">
			<destination>{bea4bf4b-3435-432f-abbf-8effe300780c}</destination>
		</relationship>
		<relationship name="masterTrack">
			<destination>{622d9a4d-11f2-4d0e-a126-9b59d6877c15}</destination>
		</relationship>
		<relationship name="mixerInput">
			<destination>{e510c8a5-9685-4de8-a915-64aea0475bad}</destination>
		</relationship>
		<relationship name="automatableProperties">
			<destination>{a66c79cb-c8cb-4d98-a23f-657d6f372c2a}</destination>
		</relationship>
		<relationship name="markerTracks">
			<destination>{2dc8b09a-7834-4db7-957b-511328362ea5}</destination>
		</relationship>
		<relationship name="groupTracks">
			<destination>{bde0ad6a-6809-4b5c-8fe3-9d884223ae6b}</destination>
		</relationship>
		<relationship name="timeline">
			<destination>{128ccc49-9003-4075-8ab2-482e41aad84f}</destination>
		</relationship>
		<relationship name="banks">
			<destination>{c2950bcd-470f-4d51-bc19-fbd253a9446e}</destination>
		</relationship>
	</object>
	<object class="EventMixer" id="{bea4bf4b-3435-432f-abbf-8effe300780c}">
		<relationship name="masterBus">
			<destination>{24495768-5189-44ee-8b92-6dbcb580accb}</destination>
		</relationship>
	</object>
	<object class="MasterTrack" id="{622d9a4d-11f2-4d0e-a126-9b59d6877c15}">
		<relationship name="mixerGroup">
			<destination>{24495768-5189-44ee-8b92-6dbcb580accb}</destination>
		</relationship>
	</object>
	<object class="MixerInput" id="{e510c8a5-9685-4de8-a915-64aea0475bad}">
		<relationship name="effectChain">
			<destination>{13b76f22-3dba-455c-ad3d-29619adeb932}</destination>
		</relationship>
		<relationship name="panner">
			<destination>{e5056214-74f5-48c4-bf74-868536748a62}</destination>
		</relationship>
		<relationship name="output">
			<destination>{7d4793fa-a677-4462-bebe-7a8cca71d6cb}</destination>
		</relationship>
	</object>
	<object class="EventAutomatableProperties" id="{a66c79cb-c8cb-4d98-a23f-657d6f372c2a}" />
	<object class="MarkerTrack" id="{2dc8b09a-7834-4db7-957b-511328362ea5}" />
	<object class="GroupTrack" id="{bde0ad6a-6809-4b5c-8fe3-9d884223ae6b}">
		<relationship name="modules">
			<destination>{06fc7149-9247-43f8-949a-c6da3d0efeb1}</destination>
		</relationship>
		<relationship name="mixerGroup">
			<destination>{55e33d41-d8ac-4e18-a43d-95a494f003a5}</destination>
		</relationship>
	</object>
	<object class="Timeline" id="{128ccc49-9003-4075-8ab2-482e41aad84f}">
		<relationship name="modules">
			<destination>{06fc7149-9247-43f8-949a-c6da3d0efeb1}</destination>
		</relationship>
		<relationship name="markers">
			<destination>{831f9dab-e11c-446d-a841-ba8e602227b8}</destination>
		</relationship>
	</object>
	<object class="EventMixerMaster" id="{24495768-5189-44ee-8b92-6dbcb580accb}">
		<relationship name="effectChain">
			<destination>{54382c53-f461-4266-92cd-38acd01a58b2}</destination>
		</relationship>
		<relationship name="panner">
			<destination>{8eb71bd6-b1a9-4734-82d8-3c6c07865a96}</destination>
		</relationship>
		<relationship name="mixer">
			<destination>{bea4bf4b-3435-432f-abbf-8effe300780c}</destination>
		</relationship>
	</object>
	<object class="MixerBusEffectChain" id="{13b76f22-3dba-455c-ad3d-29619adeb932}">
		<relationship name="effects">
			<destination>{0ee6cde1-44e6-49fc-8b55-d3ef86246403}</destination>
		</relationship>
	</object>
	<object class="MixerBusPanner" id="{e5056214-74f5-48c4-bf74-868536748a62}" />
	<object class="SoundScatterer" id="{06fc7149-9247-43f8-949a-c6da3d0efeb1}">
		<property name="length">
			<value>4</value>
		</property>
		<property name="polyphony">
			<value>1</value>
		</property>
		<property name="soundStealing">
			<value>3</value>
		</property>
		<property name="minimumTimeBetweenSounds">
			<value>8550</value>
		</property>
		<property name="maximumTimeBetweenSounds">
			<value>26000</value>
		</property>
		<property name="maximumScatterDistance">
			<value>1</value>
		</property>
		<property name="pitchRandomization">
			<value>0.5</value>
		</property>
		<relationship name="sound">
			<destination>{d2b9d1c1-92e2-4663-9514-7c0b0ebcf367}</destination>
		</relationship>
	</object>
	<object class="EventMixerGroup" id="{55e33d41-d8ac-4e18-a43d-95a494f003a5}">
		<property name="volume">
			<value>-17.5</value>
		</property>
		<property name="name">
			<value>Audio 1</value>
		</property>
		<relationship name="effectChain">
			<destination>{9d3ff3e2-684f-419e-8d42-abb4c9c8eeb9}</destination>
		</relationship>
		<relationship name="panner">
			<destination>{77b026e7-ae66-40ab-b175-90e4ab911cfb}</destination>
		</relationship>
		<relationship name="output">
			<destination>{24495768-5189-44ee-8b92-6dbcb580accb}</destination>
		</relationship>
	</object>
	<object class="LoopRegion" id="{831f9dab-e11c-446d-a841-ba8e602227b8}">
		<property name="position">
			<value>0</value>
		</property>
		<property name="length">
			<value>4</value>
		</property>
		<relationship name="timeline">
			<destination>{128ccc49-9003-4075-8ab2-482e41aad84f}</destination>
		</relationship>
		<relationship name="markerTrack">
			<destination>{2dc8b09a-7834-4db7-957b-511328362ea5}</destination>
		</relationship>
	</object>
	<object class="MixerBusEffectChain" id="{54382c53-f461-4266-92cd-38acd01a58b2}">
		<relationship name="effects">
			<destination>{19aa4651-d6d7-4b35-acbb-52f07ee538c9}</destination>
			<destination>{f6c56096-a3db-4be8-be92-37f2022c6340}</destination>
		</relationship>
	</object>
	<object class="MixerBusPanner" id="{8eb71bd6-b1a9-4734-82d8-3c6c07865a96}" />
	<object class="MixerBusFader" id="{0ee6cde1-44e6-49fc-8b55-d3ef86246403}" />
	<object class="MultiSound" id="{d2b9d1c1-92e2-4663-9514-7c0b0ebcf367}">
		<relationship name="sounds">
			<destination>{02b9b559-8da9-4bc7-bdf0-ecbd2876d99f}</destination>
			<destination>{3a7f4911-73b1-48b4-a18f-4d0e4ecc259c}</destination>
			<destination>{f0e86819-6f30-4721-a598-b49ff4f7f8a2}</destination>
		</relationship>
	</object>
	<object class="MixerBusEffectChain" id="{9d3ff3e2-684f-419e-8d42-abb4c9c8eeb9}">
		<relationship name="effects">
			<destination>{639aca4f-1a77-4e50-96db-d28203997ced}</destination>
		</relationship>
	</object>
	<object class="MixerBusPanner" id="{77b026e7-ae66-40ab-b175-90e4ab911cfb}" />
	<object class="MixerBusFader" id="{19aa4651-d6d7-4b35-acbb-52f07ee538c9}" />
	<object class="PluginEffect" id="{f6c56096-a3db-4be8-be92-37f2022c6340}">
		<relationship name="plugin">
			<destination>{40bfc416-6339-4446-a7ca-5583e22f5913}</destination>
		</relationship>
	</object>
	<object class="SingleSound" id="{02b9b559-8da9-4bc7-bdf0-ecbd2876d99f}">
		<relationship name="audioFile">
			<destination>{8676d8e6-42ac-4e3e-b61b-ec5c74810671}</destination>
		</relationship>
	</object>
	<object class="SingleSound" id="{3a7f4911-73b1-48b4-a18f-4d0e4ecc259c}">
		<relationship name="audioFile">
			<destination>{776aad64-5764-4736-bd74-d658c40fc298}</destination>
		</relationship>
	</object>
	<object class="SingleSound" id="{f0e86819-6f30-4721-a598-b49ff4f7f8a2}">
		<relationship name="audioFile">
			<destination>{581126f2-e8a8-4e92-98d6-84f3579d272c}</destination>
		</relationship>
	</object>
	<object class="MixerBusFader" id="{639aca4f-1a77-4e50-96db-d28203997ced}" />
	<object class="Plugin" id="{40bfc416-6339-4446-a7ca-5583e22f5913}">
		<property name="identifier">
			<value>Steam Audio Spatializer</value>
		</property>
		<relationship name="pluginParameters">
			<destination>{93aa0bdb-ccec-4617-8b32-799136465f84}</destination>
			<destination>{8d64f1fb-6c13-475b-a929-3e916c32539c}</destination>
			<destination>{b8d0dda7-a709-42a4-b117-7a5aad5d7f87}</destination>
			<destination>{f16a3348-26b7-4c6e-9984-41cd3be6f0b0}</destination>
			<destination>{4e15bf2d-8acc-4775-b761-5fb56373808d}</destination>
			<destination>{18b4c6f4-d60d-4c5f-9aa6-767c2c215460}</destination>
			<destination>{6613b59f-5da7-4099-a091-6c883ac4521d}</destination>
			<destination>{1d5dba2d-a056-4c33-9150-535349284e35}</destination>
			<destination>{f879c824-79ff-4e6e-ad1f-e36f5b7e1747}</destination>
			<destination>{cf2b5251-9f08-4a69-98ba-dce84c595c61}</destination>
			<destination>{b4b9a144-c98f-4361-87ca-ec5b94fee75f}</destination>
			<destination>{367a202d-2277-46f2-aad7-d4d2719c72ab}</destination>
			<destination>{fcd5d32b-8a2f-4b2a-a2c6-015b43249bae}</destination>
			<destination>{44617d7d-cec5-4fb2-874a-ee91172446cb}</destination>
			<destination>{80e54fdb-7bbe-4f71-b874-059733aa714d}</destination>
			<destination>{5aead212-49cd-4256-8943-84042d7acc93}</destination>
			<destination>{a605d00b-19f7-45de-aad5-7d1512d6829a}</destination>
			<destination>{2bea6537-9fe7-4a73-a936-fee3bbf0cd81}</destination>
			<destination>{3c3e7b9a-9bf4-480a-85d8-99cc33e61197}</destination>
			<destination>{b5fe31c6-38cb-4637-a87f-4c82daecbd78}</destination>
			<destination>{a0b8b33d-724e-4f51-b8ef-a68a7cbf0039}</destination>
			<destination>{1e9eb319-0345-4184-bfb8-a45fc6293405}</destination>
			<destination>{5cff215b-9a20-428a-855c-ea46eb2e56ba}</destination>
			<destination>{c836f226-4f09-41ae-8a58-14d994fc256e}</destination>
			<destination>{8be7d8f7-1e3d-4a60-ba88-78fa53899ebd}</destination>
			<destination>{8a64c688-604b-46f3-ad34-d137790e7d31}</destination>
			<destination>{61862c27-68a4-4e4c-95d7-3a25b810258b}</destination>
			<destination>{b37433d9-35cb-491e-884e-88b53dcab294}</destination>
			<destination>{38587f84-f92b-4b1a-b2af-8c72eca93784}</destination>
			<destination>{96d5151d-4784-4d9c-b2dd-e0d3f4b28398}</destination>
			<destination>{065c9e26-e5f1-4bc6-ab51-a9679af82c0a}</destination>
			<destination>{f878a000-5aea-4c25-81ef-82a6db119ad0}</destination>
			<destination>{1a714438-d9f9-4354-a9ec-090ffe42a652}</destination>
		</relationship>
	</object>
	<object class="DataPluginParameter" id="{93aa0bdb-ccec-4617-8b32-799136465f84}">
		<property name="name">
			<value>SourcePos</value>
		</property>
		<property name="dataType">
			<value>-2</value>
		</property>
	</object>
	<object class="DataPluginParameter" id="{8d64f1fb-6c13-475b-a929-3e916c32539c}">
		<property name="name">
			<value>OverallGain</value>
		</property>
		<property name="dataType">
			<value>-1</value>
		</property>
	</object>
	<object class="IntPluginParameter" id="{b8d0dda7-a709-42a4-b117-7a5aad5d7f87}">
		<property name="name">
			<value>ApplyDA</value>
		</property>
		<property name="value">
			<value>2</value>
		</property>
		<property name="minimumValue">
			<value>0</value>
		</property>
		<property name="maximumValue">
			<value>2</value>
		</property>
	</object>
	<object class="IntPluginParameter" id="{f16a3348-26b7-4c6e-9984-41cd3be6f0b0}">
		<property name="name">
			<value>ApplyAA</value>
		</property>
		<property name="value">
			<value>1</value>
		</property>
		<property name="minimumValue">
			<value>0</value>
		</property>
		<property name="maximumValue">
			<value>2</value>
		</property>
	</object>
	<object class="IntPluginParameter" id="{4e15bf2d-8acc-4775-b761-5fb56373808d}">
		<property name="name">
			<value>ApplyDir</value>
		</property>
		<property name="value">
			<value>0</value>
		</property>
		<property name="minimumValue">
			<value>0</value>
		</property>
		<property name="maximumValue">
			<value>2</value>
		</property>
	</object>
	<object class="IntPluginParameter" id="{18b4c6f4-d60d-4c5f-9aa6-767c2c215460}">
		<property name="name">
			<value>ApplyOccl</value>
		</property>
		<property name="value">
			<value>1</value>
		</property>
		<property name="minimumValue">
			<value>0</value>
		</property>
		<property name="maximumValue">
			<value>2</value>
		</property>
	</object>
	<object class="IntPluginParameter" id="{6613b59f-5da7-4099-a091-6c883ac4521d}">
		<property name="name">
			<value>ApplyTrans</value>
		</property>
		<property name="value">
			<value>1</value>
		</property>
		<property name="minimumValue">
			<value>0</value>
		</property>
		<property name="maximumValue">
			<value>2</value>
		</property>
	</object>
	<object class="BoolPluginParameter" id="{1d5dba2d-a056-4c33-9150-535349284e35}">
		<property name="name">
			<value>ApplyRefl</value>
		</property>
		<property name="value">
			<value>true</value>
		</property>
	</object>
	<object class="BoolPluginParameter" id="{f879c824-79ff-4e6e-ad1f-e36f5b7e1747}">
		<property name="name">
			<value>ApplyPath</value>
		</property>
		<property name="value">
			<value>false</value>
		</property>
	</object>
	<object class="IntPluginParameter" id="{cf2b5251-9f08-4a69-98ba-dce84c595c61}">
		<property name="name">
			<value>Interpolation</value>
		</property>
		<property name="value">
			<value>1</value>
		</property>
		<property name="minimumValue">
			<value>0</value>
		</property>
		<property name="maximumValue">
			<value>1</value>
		</property>
	</object>
	<object class="FloatPluginParameter" id="{b4b9a144-c98f-4361-87ca-ec5b94fee75f}">
		<property name="name">
			<value>DistAtt</value>
		</property>
		<property name="value">
			<value>1</value>
		</property>
		<property name="curve">
			<value>{(0.000000,0.000000)(1.000000,1.000000)}</value>
		</property>
	</object>
	<object class="IntPluginParameter" id="{367a202d-2277-46f2-aad7-d4d2719c72ab}">
		<property name="name">
			<value>DAType</value>
		</property>
		<property name="value">
			<value>0</value>
		</property>
		<property name="minimumValue">
			<value>0</value>
		</property>
		<property name="maximumValue">
			<value>4</value>
		</property>
	</object>
	<object class="FloatPluginParameter" id="{fcd5d32b-8a2f-4b2a-a2c6-015b43249bae}">
		<property name="name">
			<value>DAMinDist</value>
		</property>
		<property name="value">
			<value>1</value>
		</property>
		<property name="curve">
			<value>{(0.000000,0.000000)(1.000000,10000.000000)}</value>
		</property>
	</object>
	<object class="FloatPluginParameter" id="{44617d7d-cec5-4fb2-874a-ee91172446cb}">
		<property name="name">
			<value>DAMaxDist</value>
		</property>
		<property name="value">
			<value>50</value>
		</property>
		<property name="curve">
			<value>{(0.000000,0.000000)(1.000000,10000.000000)}</value>
		</property>
	</object>
	<object class="FloatPluginParameter" id="{80e54fdb-7bbe-4f71-b874-059733aa714d}">
		<property name="name">
			<value>AirAbsLow</value>
		</property>
		<property name="value">
			<value>1</value>
		</property>
		<property name="curve">
			<value>{(0.000000,0.000000)(1.000000,1.000000)}</value>
		</property>
	</object>
	<object class="FloatPluginParameter" id="{5aead212-49cd-4256-8943-84042d7acc93}">
		<property name="name">
			<value>AirAbsMid</value>
		</property>
		<property name="value">
			<value>1</value>
		</property>
		<property name="curve">
			<value>{(0.000000,0.000000)(1.000000,1.000000)}</value>
		</property>
	</object>
	<object class="FloatPluginParameter" id="{a605d00b-19f7-45de-aad5-7d1512d6829a}">
		<property name="name">
			<value>AirAbsHigh</value>
		</property>
		<property name="value">
			<value>1</value>
		</property>
		<property name="curve">
			<value>{(0.000000,0.000000)(1.000000,1.000000)}</value>
		</property>
	</object>
	<object class="FloatPluginParameter" id="{2bea6537-9fe7-4a73-a936-fee3bbf0cd81}">
		<property name="name">
			<value>Directivity</value>
		</property>
		<property name="value">
			<value>1</value>
		</property>
		<property name="curve">
			<value>{(0.000000,0.000000)(1.000000,1.000000)}</value>
		</property>
	</object>
	<object class="FloatPluginParameter" id="{3c3e7b9a-9bf4-480a-85d8-99cc33e61197}">
		<property name="name">
			<value>DipoleWeight</value>
		</property>
		<property name="value">
			<value>0.465000004</value>
		</property>
		<property name="curve">
			<value>{(0.000000,0.000000)(1.000000,1.000000)}</value>
		</property>
	</object>
	<object class="FloatPluginParameter" id="{b5fe31c6-38cb-4637-a87f-4c82daecbd78}">
		<property name="name">
			<value>DipolePower</value>
		</property>
		<property name="value">
			<value>1</value>
		</property>
		<property name="curve">
			<value>{(0.000000,1.000000)(1.000000,4.000000)}</value>
		</property>
	</object>
	<object class="FloatPluginParameter" id="{a0b8b33d-724e-4f51-b8ef-a68a7cbf0039}">
		<property name="name">
			<value>Occlusion</value>
		</property>
		<property name="value">
			<value>1</value>
		</property>
		<property name="curve">
			<value>{(0.000000,0.000000)(1.000000,1.000000)}</value>
		</property>
	</object>
	<object class="IntPluginParameter" id="{1e9eb319-0345-4184-bfb8-a45fc6293405}">
		<property name="name">
			<value>TransType</value>
		</property>
		<property name="value">
			<value>1</value>
		</property>
		<property name="minimumValue">
			<value>0</value>
		</property>
		<property name="maximumValue">
			<value>1</value>
		</property>
	</object>
	<object class="FloatPluginParameter" id="{5cff215b-9a20-428a-855c-ea46eb2e56ba}">
		<property name="name">
			<value>TransLow</value>
		</property>
		<property name="value">
			<value>1</value>
		</property>
		<property name="curve">
			<value>{(0.000000,0.000000)(1.000000,1.000000)}</value>
		</property>
	</object>
	<object class="FloatPluginParameter" id="{c836f226-4f09-41ae-8a58-14d994fc256e}">
		<property name="name">
			<value>TransMid</value>
		</property>
		<property name="value">
			<value>1</value>
		</property>
		<property name="curve">
			<value>{(0.000000,0.000000)(1.000000,1.000000)}</value>
		</property>
	</object>
	<object class="FloatPluginParameter" id="{8be7d8f7-1e3d-4a60-ba88-78fa53899ebd}">
		<property name="name">
			<value>TransHigh</value>
		</property>
		<property name="value">
			<value>1</value>
		</property>
		<property name="curve">
			<value>{(0.000000,0.000000)(1.000000,1.000000)}</value>
		</property>
	</object>
	<object class="FloatPluginParameter" id="{8a64c688-604b-46f3-ad34-d137790e7d31}">
		<property name="name">
			<value>DirMixLevel</value>
		</property>
		<property name="value">
			<value>1</value>
		</property>
		<property name="curve">
			<value>{(0.000000,0.000000)(1.000000,1.000000)}</value>
		</property>
	</object>
	<object class="BoolPluginParameter" id="{61862c27-68a4-4e4c-95d7-3a25b810258b}">
		<property name="name">
			<value>ReflBinaural</value>
		</property>
		<property name="value">
			<value>false</value>
		</property>
	</object>
	<object class="FloatPluginParameter" id="{b37433d9-35cb-491e-884e-88b53dcab294}">
		<property name="name">
			<value>ReflMixLevel</value>
		</property>
		<property name="value">
			<value>1</value>
		</property>
		<property name="curve">
			<value>{(0.000000,0.000000)(1.000000,10.000000)}</value>
		</property>
	</object>
	<object class="BoolPluginParameter" id="{38587f84-f92b-4b1a-b2af-8c72eca93784}">
		<property name="name">
			<value>PathBinaural</value>
		</property>
		<property name="value">
			<value>false</value>
		</property>
	</object>
	<object class="FloatPluginParameter" id="{96d5151d-4784-4d9c-b2dd-e0d3f4b28398}">
		<property name="name">
			<value>PathMixLevel</value>
		</property>
		<property name="value">
			<value>1</value>
		</property>
		<property name="curve">
			<value>{(0.000000,0.000000)(1.000000,10.000000)}</value>
		</property>
	</object>
	<object class="DataPluginParameter" id="{065c9e26-e5f1-4bc6-ab51-a9679af82c0a}">
		<property name="name">
			<value>SimOutputs</value>
		</property>
		<property name="dataType">
			<value>0</value>
		</property>
	</object>
	<object class="BoolPluginParameter" id="{f878a000-5aea-4c25-81ef-82a6db119ad0}">
		<property name="name">
			<value>DirectBinaural</value>
		</property>
		<property name="value">
			<value>true</value>
		</property>
	</object>
	<object class="DataPluginParameter" id="{1a714438-d9f9-4354-a9ec-090ffe42a652}">
		<property name="name">
			<value>DistRange</value>
		</property>
		<property name="dataType">
			<value>-6</value>
		</property>
	</object>
</objects>
